terminalgpt/.gitattributes
terminalgpt/__init__.py
terminalgpt/chat.py
terminalgpt/config.py
terminalgpt/conversations.py
terminalgpt/encryption.py
terminalgpt/main.py
terminalgpt/printer.py
terminalgpt-2.2.8.dist-info/LICENSE
terminalgpt-2.2.8.dist-info/METADATA
terminalgpt-2.2.8.dist-info/WHEEL
terminalgpt-2.2.8.dist-info/entry_points.txt
terminalgpt-2.2.8.dist-info/RECORD
