Metadata-Version: 2.3
Name: terminalgpt
Version: 2.2.8
Summary: AI chat assistant in your terminal powered by OpenAI ChatGPT models.
Keywords: ai,chat,terminal,openai,chatGPT,terminalGPT,assistant,devops,tool,cli,gpt,gpt-3.5,gpt-3.5-turbo,gpt-3.5-turbo-16k,gpt-4,gpt-4-32k
Author: Adam Yodinsky
Author-email: 27074934+adamyodinsky@users.noreply.github.com
Requires-Python: >=3.9,<4.0
Classifier: Programming Language :: Python :: 3
Classifier: Programming Language :: Python :: 3.9
Classifier: Programming Language :: Python :: 3.10
Classifier: Programming Language :: Python :: 3.11
Classifier: Programming Language :: Python :: 3.12
Classifier: Programming Language :: Python :: 3.13
Requires-Dist: click (>=8.1.3,<9.0.0)
Requires-Dist: colorama (>=0.4.6,<0.5.0)
Requires-Dist: cryptography (>=40.0.2,<43.0.0)
Requires-Dist: isort (>=5.12.0,<6.0.0)
Requires-Dist: openai (>=1.2.0,<2.0.0)
Requires-Dist: prompt-toolkit (>=3.0.38,<4.0.0)
Requires-Dist: pylint (>=3.0.2,<4.0.0)
Requires-Dist: pytest (>=7.3.1,<8.0.0)
Requires-Dist: rich (>=13.3.5,<14.0.0)
Requires-Dist: tiktoken (>=0.8,<1.0)
Requires-Dist: yaspin (>=2.3.0,<3.0.0)
